myCalculatorPackage32/__init__.py
myCalculatorPackage32/division/__init__.py
myCalculatorPackage32/division/divide.py
myCalculatorPackage32/multiplication/__init__.py
myCalculatorPackage32/multiplication/multiply.py
myCalculatorPackage32-0.0.2.dist-info/LICENSE.txt
myCalculatorPackage32-0.0.2.dist-info/METADATA
myCalculatorPackage32-0.0.2.dist-info/WHEEL
myCalculatorPackage32-0.0.2.dist-info/top_level.txt
myCalculatorPackage32-0.0.2.dist-info/RECORD
